setup.py
cloudantdb/__init__.py
cloudantdb/exceptions.py
cloudantdb/properties.py
cloudantdb/query.py
cloudantdb/utils.py
cloudantdb/validators.py
cloudantdb.egg-info/PKG-INFO
cloudantdb.egg-info/SOURCES.txt
cloudantdb.egg-info/dependency_links.txt
cloudantdb.egg-info/not-zip-safe
cloudantdb.egg-info/requires.txt
cloudantdb.egg-info/top_level.txt
cloudantdb/document/__init__.py
cloudantdb/document/base.py
cloudantdb/document/vanilla.py
cloudantdb/ext/__init__.py
cloudantdb/ext/django/__init__.py
cloudantdb/ext/django/document.py
cloudantdb/ext/django/forms.py
cloudantdb/ext/django/loading.py
cloudantdb/ext/django/models.py
cloudantdb/ext/django/testcases.py
cloudantdb/ext/django/testrunner.py
cloudantdb/ext/django/management/__init__.py
cloudantdb/ext/django/management/commands/__init__.py
cloudantdb/ext/django/management/commands/sync_cloudant.py
cloudantdb/loading/__init__.py
cloudantdb/loading/base.py
cloudantdb/loading/vanilla.py