Metadata-Version: 1.1
Name: cloudantdb
Version: 0.2
Summary: This project should make it easier for devs to use Cloudant with Python.
Home-page: UNKNOWN
Author: Brian Jinwright
Author-email: brian@ipoots.com
License: Apache
Keywords: cloudant,couchdb,django
Platform: UNKNOWN
Classifier: Programming Language :: Python
Classifier: Topic :: Software Development :: Libraries :: Python Modules
Classifier: Environment :: Web Environment
